{
  "ownerName": "Google",
  "resources": {
    "apps": {
      "resources": {
        "releases": {
          "resources": {
            "notes": {
              "methods": {
                "create": {
                  "request": {
                    "$ref": "GoogleFirebaseAppdistroV1alphaCreateReleaseNotesRequest"
                  },
                  "parameterOrder": [
                    "mobilesdkAppId",
                    "releaseId"
                  ],
                  "httpMethod": "POST",
                  "description": "Create release notes on a release.",
                  "flatPath": "v1alpha/apps/{mobilesdkAppId}/releases/{releaseId}/notes",
                  "parameters": {
                    "releaseId": {
                      "location": "path",
                      "type": "string",
                      "description": "Required. Release identifier",
                      "required": true
                    },
                    "mobilesdkAppId": {
                      "description": "Required. Unique id for a Firebase app of the format: {version}:{project_number}:{platform}:{hash(bundle_id)} Example: 1:581234567376:android:aa0a3c7b135e90289",
                      "required": true,
                      "location": "path",
                      "type": "string"
                    }
                  },
                  "response": {
                    "$ref": "GoogleFirebaseAppdistroV1alphaCreateReleaseNotesResponse"
                  },
                  "scopes": [
                    "https://www.googleapis.com/auth/cloud-platform"
                  ],
                  "path": "v1alpha/apps/{mobilesdkAppId}/releases/{releaseId}/notes",
                  "id": "firebaseappdistribution.apps.releases.notes.create"
                }
              }
            }
          },
          "methods": {
            "enable_access": {
              "id": "firebaseappdistribution.apps.releases.enable_access",
              "path": "v1alpha/apps/{mobilesdkAppId}/releases/{releaseId}/enable_access",
              "flatPath": "v1alpha/apps/{mobilesdkAppId}/releases/{releaseId}/enable_access",
              "parameters": {
                "releaseId": {
                  "description": "Required. Release identifier",
                  "required": true,
                  "location": "path",
                  "type": "string"
                },
                "mobilesdkAppId": {
                  "location": "path",
                  "type": "string",
                  "required": true,
                  "description": "Required. Unique id for a Firebase app of the format: {version}:{project_number}:{platform}:{hash(bundle_id)} Example: 1:581234567376:android:aa0a3c7b135e90289"
                }
              },
              "response": {
                "$ref": "GoogleFirebaseAppdistroV1alphaEnableAccessOnReleaseResponse"
              },
              "scopes": [
                "https://www.googleapis.com/auth/cloud-platform"
              ],
              "httpMethod": "POST",
              "description": "Enable access on a release for testers.",
              "parameterOrder": [
                "mobilesdkAppId",
                "releaseId"
              ],
              "request": {
                "$ref": "GoogleFirebaseAppdistroV1alphaEnableAccessOnReleaseRequest"
              }
            }
          }
        },
        "release_by_hash": {
          "methods": {
            "get": {
              "parameterOrder": [
                "mobilesdkAppId",
                "uploadHash"
              ],
              "httpMethod": "GET",
              "description": "GET Release by binary upload hash",
              "id": "firebaseappdistribution.apps.release_by_hash.get",
              "flatPath": "v1alpha/apps/{mobilesdkAppId}/release_by_hash/{uploadHash}",
              "parameters": {
                "mobilesdkAppId": {
                  "location": "path",
                  "type": "string",
                  "description": "Required. Unique id for a Firebase app of the format: {version}:{project_number}:{platform}:{hash(bundle_id)} Example: 1:581234567376:android:aa0a3c7b135e90289",
                  "required": true
                },
                "uploadHash": {
                  "description": "Required. The hash for the upload",
                  "required": true,
                  "location": "path",
                  "type": "string"
                }
              },
              "response": {
                "$ref": "GoogleFirebaseAppdistroV1alphaGetReleaseByUploadHashResponse"
              },
              "scopes": [
                "https://www.googleapis.com/auth/cloud-platform"
              ],
              "path": "v1alpha/apps/{mobilesdkAppId}/release_by_hash/{uploadHash}"
            }
          }
        },
        "upload_status": {
          "methods": {
            "get": {
              "id": "firebaseappdistribution.apps.upload_status.get",
              "flatPath": "v1alpha/apps/{mobilesdkAppId}/upload_status/{uploadToken}",
              "parameters": {
                "uploadToken": {
                  "location": "path",
                  "type": "string",
                  "required": true,
                  "description": "Required. The token for the upload"
                },
                "mobilesdkAppId": {
                  "required": true,
                  "description": "Required. Unique id for a Firebase app of the format: {version}:{project_number}:{platform}:{hash(bundle_id)} Example: 1:581234567376:android:aa0a3c7b135e90289",
                  "location": "path",
                  "type": "string"
                }
              },
              "response": {
                "$ref": "GoogleFirebaseAppdistroV1alphaGetUploadStatusResponse"
              },
              "scopes": [
                "https://www.googleapis.com/auth/cloud-platform"
              ],
              "path": "v1alpha/apps/{mobilesdkAppId}/upload_status/{uploadToken}",
              "parameterOrder": [
                "mobilesdkAppId",
                "uploadToken"
              ],
              "httpMethod": "GET",
              "description": "GET Binary upload status by token"
            }
          }
        },
        "testers": {
          "methods": {
            "getTesterUdids": {
              "httpMethod": "GET",
              "description": "Get UDIDs of tester iOS devices in a project",
              "parameterOrder": [
                "mobilesdkAppId"
              ],
              "flatPath": "v1alpha/apps/{mobilesdkAppId}/testers:getTesterUdids",
              "parameters": {
                "mobilesdkAppId": {
                  "description": "Unique id for a Firebase app of the format: {version}:{project_number}:{platform}:{hash(bundle_id)} Example: 1:581234567376:android:aa0a3c7b135e90289",
                  "required": true,
                  "location": "path",
                  "type": "string"
                },
                "project": {
                  "location": "query",
                  "type": "string",
                  "description": "The name of the project, which is the parent of testers Format: `projects/{project_number}`"
                }
              },
              "response": {
                "$ref": "GoogleFirebaseAppdistroV1alphaGetTesterUdidsResponse"
              },
              "scopes": [
                "https://www.googleapis.com/auth/cloud-platform"
              ],
              "path": "v1alpha/apps/{mobilesdkAppId}/testers:getTesterUdids",
              "id": "firebaseappdistribution.apps.testers.getTesterUdids"
            }
          }
        }
      },
      "methods": {
        "getJwt": {
          "id": "firebaseappdistribution.apps.getJwt",
          "flatPath": "v1alpha/apps/{mobilesdkAppId}/jwt",
          "parameters": {
            "mobilesdkAppId": {
              "description": "Required. Unique id for a Firebase app of the format: {version}:{project_number}:{platform}:{hash(bundle_id)} Example: 1:581234567376:android:aa0a3c7b135e90289",
              "required": true,
              "location": "path",
              "type": "string"
            }
          },
          "response": {
            "$ref": "GoogleFirebaseAppdistroV1alphaJwt"
          },
          "scopes": [
            "https://www.googleapis.com/auth/cloud-platform"
          ],
          "path": "v1alpha/apps/{mobilesdkAppId}/jwt",
          "httpMethod": "GET",
          "description": "Get a JWT token",
          "parameterOrder": [
            "mobilesdkAppId"
          ]
        },
        "get": {
          "id": "firebaseappdistribution.apps.get",
          "flatPath": "v1alpha/apps/{mobilesdkAppId}",
          "parameters": {
            "appView": {
              "location": "query",
              "enum": [
                "APP_VIEW_UNSPECIFIED",
                "BASIC",
                "FULL"
              ],
              "type": "string",
              "enumDescriptions": [
                "The default / unset value. The API will default to the BASIC view.",
                "Include everything except aab_state.",
                "Include everything."
              ],
              "description": "App view. When unset or set to BASIC, returns an App with everything set except for aab_state. When set to FULL, returns an App with aab_state set."
            },
            "mobilesdkAppId": {
              "required": true,
              "description": "Unique id for a Firebase app of the format: {version}:{project_number}:{platform}:{hash(bundle_id)} Example: 1:581234567376:android:aa0a3c7b135e90289",
              "location": "path",
              "type": "string"
            }
          },
          "response": {
            "$ref": "GoogleFirebaseAppdistroV1alphaApp"
          },
          "scopes": [
            "https://www.googleapis.com/auth/cloud-platform"
          ],
          "path": "v1alpha/apps/{mobilesdkAppId}",
          "httpMethod": "GET",
          "description": "Get the app, if it exists",
          "parameterOrder": [
            "mobilesdkAppId"
          ]
        }
      }
    },
    "projects": {
      "methods": {
        "getTestQuota": {
          "flatPath": "v1alpha/projects/{projectsId}/testQuota",
          "parameters": {
            "name": {
              "location": "path",
              "pattern": "^projects/[^/]+/testQuota$",
              "required": true,
              "description": "Required. The name of the `TestQuota` resource to retrieve. Format: `projects/{project_number}/testQuota`",
              "type": "string"
            }
          },
          "response": {
            "$ref": "GoogleFirebaseAppdistroV1alphaTestQuota"
          },
          "scopes": [
            "https://www.googleapis.com/auth/cloud-platform"
          ],
          "path": "v1alpha/{+name}",
          "id": "firebaseappdistribution.projects.getTestQuota",
          "httpMethod": "GET",
          "description": "Get information about the quota for `ReleaseTests`.",
          "parameterOrder": [
            "name"
          ]
        }
      },
      "resources": {
        "apps": {
          "methods": {
            "getTestConfig": {
              "httpMethod": "GET",
              "description": "Gets configuration for automated tests.",
              "parameterOrder": [
                "name"
              ],
              "id": "firebaseappdistribution.projects.apps.getTestConfig",
              "flatPath": "v1alpha/projects/{projectsId}/apps/{appsId}/testConfig",
              "parameters": {
                "name": {
                  "pattern": "^projects/[^/]+/apps/[^/]+/testConfig$",
                  "location": "path",
                  "type": "string",
                  "description": "Required. The name of the `TestConfig` resource to retrieve. Format: `projects/{project_number}/apps/{app}/testConfig`",
                  "required": true
                }
              },
              "response": {
                "$ref": "GoogleFirebaseAppdistroV1alphaTestConfig"
              },
              "scopes": [
                "https://www.googleapis.com/auth/cloud-platform"
              ],
              "path": "v1alpha/{+name}"
            },
            "updateTestConfig": {
              "path": "v1alpha/{+name}",
              "flatPath": "v1alpha/projects/{projectsId}/apps/{appsId}/testConfig",
              "parameters": {
                "name": {
                  "description": "Identifier. The name of the test configuration resource. Format: `projects/{project_number}/apps/{app}/testConfig`",
                  "required": true,
                  "type": "string",
                  "pattern": "^projects/[^/]+/apps/[^/]+/testConfig$",
                  "location": "path"
                },
                "updateMask": {
                  "location": "query",
                  "type": "string",
                  "format": "google-fieldmask",
                  "description": "Optional. The list of fields to update."
                }
              },
              "response": {
                "$ref": "GoogleFirebaseAppdistroV1alphaTestConfig"
              },
              "scopes": [
                "https://www.googleapis.com/auth/cloud-platform"
              ],
              "id": "firebaseappdistribution.projects.apps.updateTestConfig",
              "httpMethod": "PATCH",
              "description": "Updates automated test configuration.",
              "parameterOrder": [
                "name"
              ],
              "request": {
                "$ref": "GoogleFirebaseAppdistroV1alphaTestConfig"
              }
            }
          },
          "resources": {
            "releases": {
              "resources": {
                "tests": {
                  "methods": {
                    "get": {
                      "httpMethod": "GET",
                      "description": "Get results for automated test run on release.",
                      "parameterOrder": [
                        "name"
                      ],
                      "flatPath": "v1alpha/projects/{projectsId}/apps/{appsId}/releases/{releasesId}/tests/{testsId}",
                      "parameters": {
                        "name": {
                          "required": true,
                          "description": "Required. The name of the release test resource. Format: `projects/{project_number}/apps/{app}/releases/{release}/tests/{test}`",
                          "type": "string",
                          "location": "path",
                          "pattern": "^projects/[^/]+/apps/[^/]+/releases/[^/]+/tests/[^/]+$"
                        }
                      },
                      "response": {
                        "$ref": "GoogleFirebaseAppdistroV1alphaReleaseTest"
                      },
                      "scopes": [
                        "https://www.googleapis.com/auth/cloud-platform"
                      ],
                      "path": "v1alpha/{+name}",
                      "id": "firebaseappdistribution.projects.apps.releases.tests.get"
                    },
                    "list": {
                      "id": "firebaseappdistribution.projects.apps.releases.tests.list",
                      "flatPath": "v1alpha/projects/{projectsId}/apps/{appsId}/releases/{releasesId}/tests",
                      "parameters": {
                        "pageToken": {
                          "description": "Optional. A page token, received from a previous `ListReleaseTests` call. Provide this to retrieve the subsequent page.",
                          "location": "query",
                          "type": "string"
                        },
                        "parent": {
                          "description": "Required. The name of the release resource, which is the parent of the tests Format: `projects/{project_number}/apps/{app}/releases/{release}`",
                          "required": true,
                          "type": "string",
                          "pattern": "^projects/[^/]+/apps/[^/]+/releases/[^/]+$",
                          "location": "path"
                        },
                        "view": {
                          "location": "query",
                          "enum": [
                            "RELEASE_TEST_VIEW_UNSPECIFIED",
                            "RELEASE_TEST_VIEW_BASIC",
                            "RELEASE_TEST_VIEW_FULL"
                          ],
                          "description": "Optional. The requested view on the returned ReleaseTests. Defaults to the basic view.",
                          "type": "string",
                          "enumDescriptions": [
                            "The default / unset value. The default view depends on the RPC.",
                            "Include basic metadata about the release test and its status, but not the full result details. This is the default value for ListReleaseTests.",
                            "Include everything."
                          ]
                        },
                        "pageSize": {
                          "location": "query",
                          "type": "integer",
                          "format": "int32",
                          "description": "Optional. The maximum number of tests to return. The service may return fewer than this value."
                        }
                      },
                      "response": {
                        "$ref": "GoogleFirebaseAppdistroV1alphaListReleaseTestsResponse"
                      },
                      "scopes": [
                        "https://www.googleapis.com/auth/cloud-platform"
                      ],
                      "path": "v1alpha/{+parent}/tests",
                      "parameterOrder": [
                        "parent"
                      ],
                      "httpMethod": "GET",
                      "description": "List results for automated tests run on release."
                    },
                    "cancel": {
                      "httpMethod": "GET",
                      "description": "Abort automated test run on release.",
                      "parameterOrder": [
                        "name"
                      ],
                      "id": "firebaseappdistribution.projects.apps.releases.tests.cancel",
                      "flatPath": "v1alpha/projects/{projectsId}/apps/{appsId}/releases/{releasesId}/tests/{testsId}:cancel",
                      "parameters": {
                        "name": {
                          "type": "string",
                          "description": "Required. The name of the release test resource. Format: `projects/{project_number}/apps/{app}/releases/{release}/tests/{test}`",
                          "required": true,
                          "pattern": "^projects/[^/]+/apps/[^/]+/releases/[^/]+/tests/[^/]+$",
                          "location": "path"
                        }
                      },
                      "response": {
                        "$ref": "GoogleFirebaseAppdistroV1alphaCancelReleaseTestResponse"
                      },
                      "scopes": [
                        "https://www.googleapis.com/auth/cloud-platform"
                      ],
                      "path": "v1alpha/{+name}:cancel"
                    },
                    "create": {
                      "flatPath": "v1alpha/projects/{projectsId}/apps/{appsId}/releases/{releasesId}/tests",
                      "parameters": {
                        "parent": {
                          "pattern": "^projects/[^/]+/apps/[^/]+/releases/[^/]+$",
                          "location": "path",
                          "type": "string",
                          "description": "Required. The name of the release resource, which is the parent of the test Format: `projects/{project_number}/apps/{app}/releases/{release}`",
                          "required": true
                        },
                        "releaseTestId": {
                          "description": "Optional. The ID to use for the test, which will become the final component of the test's resource name. This value should be 4-63 characters, and valid characters are /a-z-/. If it is not provided one will be automatically generated.",
                          "location": "query",
                          "type": "string"
                        }
                      },
                      "response": {
                        "$ref": "GoogleFirebaseAppdistroV1alphaReleaseTest"
                      },
                      "scopes": [
                        "https://www.googleapis.com/auth/cloud-platform"
                      ],
                      "path": "v1alpha/{+parent}/tests",
                      "id": "firebaseappdistribution.projects.apps.releases.tests.create",
                      "httpMethod": "POST",
                      "description": "Run automated test(s) on release.",
                      "request": {
                        "$ref": "GoogleFirebaseAppdistroV1alphaReleaseTest"
                      },
                      "parameterOrder": [
                        "parent"
                      ]
                    }
                  }
                }
              }
            },
            "testCases": {
              "methods": {
                "get": {
                  "id": "firebaseappdistribution.projects.apps.testCases.get",
                  "flatPath": "v1alpha/projects/{projectsId}/apps/{appsId}/testCases/{testCasesId}",
                  "parameters": {
                    "name": {
                      "required": true,
                      "description": "Required. The name of the test case resource to retrieve. Format: `projects/{project_number}/apps/{app}/testCases/{test_case}`",
                      "type": "string",
                      "location": "path",
                      "pattern": "^projects/[^/]+/apps/[^/]+/testCases/[^/]+$"
                    }
                  },
                  "response": {
                    "$ref": "GoogleFirebaseAppdistroV1alphaTestCase"
                  },
                  "scopes": [
                    "https://www.googleapis.com/auth/cloud-platform"
                  ],
                  "path": "v1alpha/{+name}",
                  "httpMethod": "GET",
                  "description": "Get a test case.",
                  "parameterOrder": [
                    "name"
                  ]
                },
                "delete": {
                  "id": "firebaseappdistribution.projects.apps.testCases.delete",
                  "path": "v1alpha/{+name}",
                  "flatPath": "v1alpha/projects/{projectsId}/apps/{appsId}/testCases/{testCasesId}",
                  "parameters": {
                    "name": {
                      "required": true,
                      "description": "Required. The name of the test case resource to delete. Format: `projects/{project_number}/apps/{app}/testCases/{test_case}`",
                      "type": "string",
                      "location": "path",
                      "pattern": "^projects/[^/]+/apps/[^/]+/testCases/[^/]+$"
                    }
                  },
                  "response": {
                    "$ref": "GoogleProtobufEmpty"
                  },
                  "scopes": [
                    "https://www.googleapis.com/auth/cloud-platform"
                  ],
                  "parameterOrder": [
                    "name"
                  ],
                  "httpMethod": "DELETE",
                  "description": "Delete a test case."
                },
                "create": {
                  "flatPath": "v1alpha/projects/{projectsId}/apps/{appsId}/testCases",
                  "parameters": {
                    "parent": {
                      "location": "path",
                      "pattern": "^projects/[^/]+/apps/[^/]+$",
                      "required": true,
                      "description": "Required. The parent resource where this test case will be created. Format: `projects/{project_number}/apps/{app}`",
                      "type": "string"
                    },
                    "testCaseId": {
                      "location": "query",
                      "type": "string",
                      "description": "Optional. The ID to use for the test case, which will become the final component of the test case's resource name. This value should be 4-63 characters, and valid characters are /a-z-/."
                    }
                  },
                  "response": {
                    "$ref": "GoogleFirebaseAppdistroV1alphaTestCase"
                  },
                  "scopes": [
                    "https://www.googleapis.com/auth/cloud-platform"
                  ],
                  "path": "v1alpha/{+parent}/testCases",
                  "id": "firebaseappdistribution.projects.apps.testCases.create",
                  "request": {
                    "$ref": "GoogleFirebaseAppdistroV1alphaTestCase"
                  },
                  "parameterOrder": [
                    "parent"
                  ],
                  "httpMethod": "POST",
                  "description": "Create a new test case."
                },
                "patch": {
                  "httpMethod": "PATCH",
                  "description": "Update a test case.",
                  "parameterOrder": [
                    "name"
                  ],
                  "request": {
                    "$ref": "GoogleFirebaseAppdistroV1alphaTestCase"
                  },
                  "id": "firebaseappdistribution.projects.apps.testCases.patch",
                  "path": "v1alpha/{+name}",
                  "flatPath": "v1alpha/projects/{projectsId}/apps/{appsId}/testCases/{testCasesId}",
                  "parameters": {
                    "name": {
                      "type": "string",
                      "description": "Identifier. The name of the test case resource. Format: `projects/{project_number}/apps/{app}/testCases/{test_case}`",
                      "required": true,
                      "pattern": "^projects/[^/]+/apps/[^/]+/testCases/[^/]+$",
                      "location": "path"
                    },
                    "allowMissing": {
                      "description": "Optional. If set to true, and the test case is not found, a new test case will be created.",
                      "location": "query",
                      "type": "boolean"
                    }
                  },
                  "response": {
                    "$ref": "GoogleFirebaseAppdistroV1alphaTestCase"
                  },
                  "scopes": [
                    "https://www.googleapis.com/auth/cloud-platform"
                  ]
                },
                "batchUpdate": {
                  "path": "v1alpha/{+parent}/testCases:batchUpdate",
                  "flatPath": "v1alpha/projects/{projectsId}/apps/{appsId}/testCases:batchUpdate",
                  "parameters": {
                    "parent": {
                      "location": "path",
                      "pattern": "^projects/[^/]+/apps/[^/]+$",
                      "type": "string",
                      "required": true,
                      "description": "Required. The parent resource of the test cases being updated. Format: `projects/{project_number}/apps/{app}`"
                    }
                  },
                  "response": {
                    "$ref": "GoogleFirebaseAppdistroV1alphaBatchUpdateTestCasesResponse"
                  },
                  "scopes": [
                    "https://www.googleapis.com/auth/cloud-platform"
                  ],
                  "id": "firebaseappdistribution.projects.apps.testCases.batchUpdate",
                  "parameterOrder": [
                    "parent"
                  ],
                  "request": {
                    "$ref": "GoogleFirebaseAppdistroV1alphaBatchUpdateTestCasesRequest"
                  },
                  "httpMethod": "POST",
                  "description": "Updates multiple test cases."
                },
                "clearTestCaseCache": {
                  "flatPath": "v1alpha/projects/{projectsId}/apps/{appsId}/testCases/{testCasesId}:clearTestCaseCache",
                  "parameters": {
                    "testCase": {
                      "type": "string",
                      "description": "Required. The name of the test case resource for which to clear the cache. Format: `projects/{project_number}/apps/{app}/testCases/{test_case}`",
                      "required": true,
                      "pattern": "^projects/[^/]+/apps/[^/]+/testCases/[^/]+$",
                      "location": "path"
                    }
                  },
                  "response": {
                    "$ref": "GoogleFirebaseAppdistroV1alphaClearTestCaseCacheResponse"
                  },
                  "scopes": [
                    "https://www.googleapis.com/auth/cloud-platform"
                  ],
                  "path": "v1alpha/{+testCase}:clearTestCaseCache",
                  "id": "firebaseappdistribution.projects.apps.testCases.clearTestCaseCache",
                  "httpMethod": "POST",
                  "description": "Clears cached test runs for a specific test case and device(s).",
                  "request": {
                    "$ref": "GoogleFirebaseAppdistroV1alphaClearTestCaseCacheRequest"
                  },
                  "parameterOrder": [
                    "testCase"
                  ]
                },
                "list": {
                  "flatPath": "v1alpha/projects/{projectsId}/apps/{appsId}/testCases",
                  "parameters": {
                    "parent": {
                      "description": "Required. The parent resource from which to list test cases. Format: `projects/{project_number}/apps/{app}`",
                      "required": true,
                      "type": "string",
                      "pattern": "^projects/[^/]+/apps/[^/]+$",
                      "location": "path"
                    },
                    "pageToken": {
                      "description": "Optional. A page token, received from a previous `ListTestCases` call. Provide this to retrieve the subsequent page. When paginating, all other parameters provided to `ListTestCases` must match the call that provided the page token.",
                      "location": "query",
                      "type": "string"
                    },
                    "pageSize": {
                      "description": "Optional. The maximum number of test cases to return. The service may return fewer than this value. If unspecified, at most 50 test cases will be returned. The maximum value is 1000; values above 1000 will be coerced to 1000.",
                      "format": "int32",
                      "location": "query",
                      "type": "integer"
                    }
                  },
                  "response": {
                    "$ref": "GoogleFirebaseAppdistroV1alphaListTestCasesResponse"
                  },
                  "scopes": [
                    "https://www.googleapis.com/auth/cloud-platform"
                  ],
                  "path": "v1alpha/{+parent}/testCases",
                  "id": "firebaseappdistribution.projects.apps.testCases.list",
                  "parameterOrder": [
                    "parent"
                  ],
                  "httpMethod": "GET",
                  "description": "List test cases."
                },
                "batchDelete": {
                  "httpMethod": "POST",
                  "description": "Deletes multiple test cases.",
                  "request": {
                    "$ref": "GoogleFirebaseAppdistroV1alphaBatchDeleteTestCasesRequest"
                  },
                  "parameterOrder": [
                    "parent"
                  ],
                  "id": "firebaseappdistribution.projects.apps.testCases.batchDelete",
                  "flatPath": "v1alpha/projects/{projectsId}/apps/{appsId}/testCases:batchDelete",
                  "parameters": {
                    "parent": {
                      "type": "string",
                      "description": "Required. The parent resource of the test cases being deleted. Format: `projects/{project_number}/apps/{app}`",
                      "required": true,
                      "pattern": "^projects/[^/]+/apps/[^/]+$",
                      "location": "path"
                    }
                  },
                  "response": {
                    "$ref": "GoogleProtobufEmpty"
                  },
                  "scopes": [
                    "https://www.googleapis.com/auth/cloud-platform"
                  ],
                  "path": "v1alpha/{+parent}/testCases:batchDelete"
                }
              }
            }
          }
        },
        "testers": {
          "methods": {
            "getUdids": {
              "id": "firebaseappdistribution.projects.testers.getUdids",
              "flatPath": "v1alpha/projects/{projectsId}/testers:udids",
              "parameters": {
                "project": {
                  "pattern": "^projects/[^/]+$",
                  "location": "path",
                  "type": "string",
                  "description": "The name of the project, which is the parent of testers Format: `projects/{project_number}`",
                  "required": true
                },
                "mobilesdkAppId": {
                  "location": "query",
                  "type": "string",
                  "description": "Unique id for a Firebase app of the format: {version}:{project_number}:{platform}:{hash(bundle_id)} Example: 1:581234567376:android:aa0a3c7b135e90289"
                }
              },
              "response": {
                "$ref": "GoogleFirebaseAppdistroV1alphaGetTesterUdidsResponse"
              },
              "scopes": [
                "https://www.googleapis.com/auth/cloud-platform"
              ],
              "path": "v1alpha/{+project}/testers:udids",
              "parameterOrder": [
                "project"
              ],
              "httpMethod": "GET",
              "description": "Get UDIDs of tester iOS devices in a project"
            }
          }
        }
      }
    }
  },
  "fullyEncodeReservedExpansion": true,
  "version": "v1alpha",
  "icons": {
    "x16": "http://www.google.com/images/icons/product/search-16.gif",
    "x32": "http://www.google.com/images/icons/product/search-32.gif"
  },
  "name": "firebaseappdistribution",
  "revision": "20260403",
  "discoveryVersion": "v1",
  "ownerDomain": "google.com",
  "rootUrl": "https://firebaseappdistribution.googleapis.com/",
  "title": "Firebase App Distribution API",
  "auth": {
    "oauth2": {
      "scopes": {
        "https://www.googleapis.com/auth/cloud-platform": {
          "description": "See, edit, configure, and delete your Google Cloud data and see the email address for your Google Account."
        }
      }
    }
  },
  "basePath": "",
  "canonicalName": "Firebase App Distribution",
  "protocol": "rest",
  "kind": "discovery#restDescription",
  "baseUrl": "https://firebaseappdistribution.googleapis.com/",
  "mtlsRootUrl": "https://firebaseappdistribution.mtls.googleapis.com/",
  "servicePath": "",
  "id": "firebaseappdistribution:v1alpha",
  "documentationLink": "https://firebase.google.com/products/app-distribution",
  "parameters": {
    "fields": {
      "type": "string",
      "location": "query",
      "description": "Selector specifying which fields to include in a partial response."
    },
    "upload_protocol": {
      "type": "string",
      "location": "query",
      "description": "Upload protocol for media (e.g. \"raw\", \"multipart\")."
    },
    "alt": {
      "default": "json",
      "enum": [
        "json",
        "media",
        "proto"
      ],
      "location": "query",
      "description": "Data format for response.",
      "type": "string",
      "enumDescriptions": [
        "Responses with Content-Type of application/json",
        "Media download with context-dependent Content-Type",
        "Responses with Content-Type of application/x-protobuf"
      ]
    },
    "prettyPrint": {
      "type": "boolean",
      "location": "query",
      "default": "true",
      "description": "Returns response with indentations and line breaks."
    },
    "$.xgafv": {
      "type": "string",
      "enumDescriptions": [
        "v1 error format",
        "v2 error format"
      ],
      "description": "V1 error format.",
      "enum": [
        "1",
        "2"
      ],
      "location": "query"
    },
    "key": {
      "type": "string",
      "location": "query",
      "description": "API key. Your API key identifies your project and provides you with API access, quota, and reports. Required unless you provide an OAuth 2.0 token."
    },
    "callback": {
      "description": "JSONP",
      "type": "string",
      "location": "query"
    },
    "uploadType": {
      "type": "string",
      "location": "query",
      "description": "Legacy upload protocol for media (e.g. \"media\", \"multipart\")."
    },
    "access_token": {
      "type": "string",
      "location": "query",
      "description": "OAuth access token."
    },
    "oauth_token": {
      "description": "OAuth 2.0 token for the current user.",
      "type": "string",
      "location": "query"
    },
    "quotaUser": {
      "type": "string",
      "location": "query",
      "description": "Available to use for quota purposes for server-side applications. Can be any arbitrary string assigned to a user, but should not exceed 40 characters."
    }
  },
  "version_module": true,
  "schemas": {
    "GoogleFirebaseAppdistroV1alphaRoboStats": {
      "description": "Statistics collected during a Robo test.",
      "properties": {
        "crawlDuration": {
          "description": "Output only. Duration of crawl.",
          "readOnly": true,
          "type": "string",
          "format": "google-duration"
        },
        "distinctVisitedScreens": {
          "type": "integer",
          "format": "int32",
          "description": "Output only. Number of distinct screens visited.",
          "readOnly": true
        },
        "actionsPerformed": {
          "description": "Output only. Number of actions that crawler performed.",
          "readOnly": true,
          "format": "int32",
          "type": "integer"
        },
        "mainActivityCrawlTimedOut": {
          "type": "boolean",
          "description": "Output only. Whether the main activity crawl timed out.",
          "readOnly": true
        }
      },
      "type": "object",
      "id": "GoogleFirebaseAppdistroV1alphaRoboStats"
    },
    "GoogleFirebaseAppdistroV1alphaDeviceAction": {
      "description": "A high level action taken by the AI on the device, potentially involving multiple taps, text entries, waits, etc.",
      "properties": {
        "description": {
          "description": "Output only. A short description of the high level action taken by the AI agent.",
          "readOnly": true,
          "type": "string"
        },
        "deviceInteractions": {
          "type": "array",
          "description": "Output only. The interactions made with the device as part of this higher level action taken by the agent, such as taps, text entries, waits, etc.",
          "readOnly": true,
          "items": {
            "$ref": "GoogleFirebaseAppdistroV1alphaDeviceInteraction"
          }
        }
      },
      "type": "object",
      "id": "GoogleFirebaseAppdistroV1alphaDeviceAction"
    },
    "GoogleFirebaseAppdistroV1alphaCreateReleaseNotesResponse": {
      "id": "GoogleFirebaseAppdistroV1alphaCreateReleaseNotesResponse",
      "type": "object",
      "description": "The response message for `CreateReleaseNotes`.",
      "properties": {}
    },
    "GoogleFirebaseAppdistroV1alphaLoginCredential": {
      "id": "GoogleFirebaseAppdistroV1alphaLoginCredential",
      "type": "object",
      "description": "Login credential for automated tests",
      "properties": {
        "google": {
          "description": "Optional. Are these credentials for Google?",
          "type": "boolean"
        },
        "username": {
          "description": "Optional. Username for automated tests",
          "type": "string"
        },
        "password": {
          "type": "string",
          "description": "Optional. Password for automated tests"
        },
        "fieldHints": {
          "description": "Optional. Hints to the crawler for identifying input fields",
          "$ref": "GoogleFirebaseAppdistroV1alphaLoginCredentialFieldHints"
        }
      }
    },
    "GoogleFirebaseAppdistroV1alphaDeviceInteraction": {
      "description": "An interaction with the device, such as a tap, text entry, wait, etc.",
      "properties": {
        "enterText": {
          "description": "Output only. A text entry action, that enters text into a particular text field, clearing any existing text in the field. Unlike `text_input` this action does not require any other actions such as a tap to be performed before it can enter the text.",
          "readOnly": true,
          "$ref": "GoogleFirebaseAppdistroV1alphaDeviceInteractionEnterText"
        },
        "wait": {
          "description": "Output only. A wait action.",
          "readOnly": true,
          "$ref": "GoogleFirebaseAppdistroV1alphaDeviceInteractionWait"
        },
        "backAction": {
          "description": "Output only. A back action.",
          "readOnly": true,
          "$ref": "GoogleFirebaseAppdistroV1alphaDeviceInteractionBack"
        },
        "textInput": {
          "type": "string",
          "description": "Output only. A text input action, that types some text into whatever field is currently focused, if any. Unlike `enter_text` this action requires that the field be brought into focus first, for example by emitting a tap action before this one.",
          "readOnly": true
        },
        "screenshot": {
          "description": "Output only. The screenshot used in the context of this action. The screen may have changed before the action was actually taken.",
          "readOnly": true,
          "$ref": "GoogleFirebaseAppdistroV1alphaScreenshot"
        },
        "longPress": {
          "description": "Output only. A long press (tap and hold) action.",
          "readOnly": true,
          "$ref": "AndroidxCrawlerOutputPoint"
        },
        "tap": {
          "description": "Output only. A tap action.",
          "readOnly": true,
          "$ref": "AndroidxCrawlerOutputPoint"
        },
        "dragAndDrop": {
          "description": "Output only. A drag and drop action.",
          "readOnly": true,
          "$ref": "GoogleFirebaseAppdistroV1alphaDeviceInteractionDragAndDrop"
        },
        "swipe": {
          "description": "Output only. A swipe action.",
          "readOnly": true,
          "$ref": "GoogleFirebaseAppdistroV1alphaDeviceInteractionSwipe"
        },
        "keyCode": {
          "type": "string",
          "description": "Output only. Key code for a key event action.",
          "readOnly": true
        }
      },
      "id": "GoogleFirebaseAppdistroV1alphaDeviceInteraction",
      "type": "object"
    },
    "GoogleFirebaseAppdistroV1alphaClearTestCaseCacheResponse": {
      "type": "object",
      "id": "GoogleFirebaseAppdistroV1alphaClearTestCaseCacheResponse",
      "description": "Response empty (google.protobuf.Empty) message for `ClearTestCaseCache`",
      "properties": {}
    },
    "GoogleFirebaseAppdistroV1alphaTestCase": {
      "description": "AI test cases",
      "properties": {
        "displayName": {
          "description": "Required. Display name of the test case.",
          "type": "string"
        },
        "aiInstructions": {
          "description": "Optional. Instructions for AI driven test.",
          "$ref": "GoogleFirebaseAppdistroV1alphaAiInstructions"
        },
        "createTime": {
          "type": "string",
          "format": "google-datetime",
          "description": "Output only. Timestamp when the test case was created",
          "readOnly": true
        },
        "prerequisiteTestCase": {
          "type": "string",
          "description": "Optional. Test case that must be run before this test case."
        },
        "dependentTestCases": {
          "items": {
            "type": "string"
          },
          "description": "Output only. Other test cases that depend on this test case as a prerequisite.",
          "readOnly": true,
          "type": "array"
        },
        "name": {
          "description": "Identifier. The name of the test case resource. Format: `projects/{project_number}/apps/{app}/testCases/{test_case}`",
          "type": "string"
        }
      },
      "id": "GoogleFirebaseAppdistroV1alphaTestCase",
      "type": "object"
    },
    "GoogleFirebaseAppdistroV1alphaReleaseNotes": {
      "id": "GoogleFirebaseAppdistroV1alphaReleaseNotes",
      "type": "object",
      "description": "Release notes for a release.",
      "properties": {
        "releaseNotes": {
          "type": "string",
          "description": "The actual release notes text from the user."
        }
      }
    },
    "GoogleFirebaseAppdistroV1alphaGoalDetails": {
      "description": "Details for a goal step.",
      "properties": {
        "goalActions": {
          "type": "array",
          "description": "Output only. The actions taken by the AI while attempting to accomplish the goal.",
          "readOnly": true,
          "items": {
            "$ref": "GoogleFirebaseAppdistroV1alphaGoalAction"
          }
        }
      },
      "type": "object",
      "id": "GoogleFirebaseAppdistroV1alphaGoalDetails"
    },
    "GoogleFirebaseAppdistroV1alphaGoalAction": {
      "description": "An action taken by the AI agent while attempting to accomplish a goal.",
      "properties": {
        "explanation": {
          "type": "string",
          "description": "Output only. An explanation justifying why the action was taken.",
          "readOnly": true
        },
        "debugInfo": {
          "description": "Output only. Debug information explaining why the agent to the specific action.",
          "readOnly": true,
          "$ref": "GoogleFirebaseAppdistroV1alphaGoalActionDebugInfo"
        },
        "deviceAction": {
          "description": "Output only. A high level action taken by the AI on the device.",
          "readOnly": true,
          "$ref": "GoogleFirebaseAppdistroV1alphaDeviceAction"
        },
        "terminalAction": {
          "description": "Output only. An action taken by the AI to end the goal.",
          "readOnly": true,
          "$ref": "GoogleFirebaseAppdistroV1alphaTerminalAction"
        },
        "cachingType": {
          "type": "string",
          "enumDescriptions": [
            "Caching type unspecified.",
            "The model alone was used to determine the action with no caching.",
            "The model used information from a previous successful run to determine the action.",
            "The action was replayed from a previous successful run without model input."
          ],
          "description": "Output only. The type of caching used to determine the action.",
          "enum": [
            "CACHING_TYPE_UNSPECIFIED",
            "NO_CACHING",
            "CACHE_AND_MODEL",
            "CACHE_ONLY"
          ],
          "readOnly": true
        },
        "startTime": {
          "type": "string",
          "format": "google-datetime",
          "description": "Output only. The time at which the action started.",
          "readOnly": true
        }
      },
      "id": "GoogleFirebaseAppdistroV1alphaGoalAction",
      "type": "object"
    },
    "GoogleFirebaseAppdistroV1alphaJwt": {
      "type": "object",
      "id": "GoogleFirebaseAppdistroV1alphaJwt",
      "description": "A JWT token.",
      "properties": {
        "token": {
          "description": "The JWT token (three Base64URL-encoded strings joined by dots).",
          "type": "string"
        }
      }
    },
    "GoogleFirebaseAppdistroV1alphaGetUploadStatusResponse": {
      "description": "The response message for `GetUploadStatus`.",
      "properties": {
        "status": {
          "description": "The status of the upload",
          "type": "string",
          "enumDescriptions": [
            "Status unspecified.",
            "The upload is in progress.",
            "The binary has already been uploaded.",
            "The upload was successful.",
            "The upload failed."
          ],
          "enum": [
            "STATUS_UNSPECIFIED",
            "IN_PROGRESS",
            "ALREADY_UPLOADED",
            "SUCCESS",
            "ERROR"
          ]
        },
        "release": {
          "description": "The release that was created from the upload (only set on \"SUCCESS\")",
          "$ref": "GoogleFirebaseAppdistroV1alphaRelease"
        },
        "message": {
          "type": "string",
          "description": "Any additional context for the given upload status (e.g. error message) Meant to be displayed to the client"
        },
        "errorCode": {
          "type": "string",
          "enumDescriptions": [
            "",
            "",
            "",
            "",
            "",
            "",
            "",
            "",
            "",
            "",
            "",
            "",
            "",
            "",
            "",
            "",
            "",
            "",
            "",
            "",
            "",
            "",
            "Happens if the Firebase app no longer exists by the time of extraction"
          ],
          "enum": [
            "ERROR_UNSPECIFIED",
            "INVALID_ZIP",
            "MISSING_PLIST",
            "MISSING_PROFILE",
            "VERSION_TOO_LONG",
            "MISSING_UUIDS",
            "MISSING_RESOURCES",
            "MISSING_MANIFEST",
            "IOS_METADATA_ERROR",
            "ANDROID_METADATA_ERROR",
            "UNSUPPORTED_PLATFORM_TYPE",
            "BUNDLE_ID_MISMATCH",
            "APK_NOT_ZIP_ALIGNED",
            "INVALID_CERTIFICATE",
            "APK_TOO_LARGE",
            "AAB_NOT_PUBLISHED",
            "INVALID_PLIST_DEVICE_FAMILIES",
            "AAB_TOS_NOT_ACCEPTED",
            "APP_NAME_TOO_LONG",
            "AAB_DEVELOPER_ACCOUNT_NOT_LINKED",
            "AAB_NO_APP_WITH_GIVEN_PACKAGE_NAME_IN_ACCOUNT",
            "AAB_UPLOAD_ERROR",
            "APP_NOT_FOUND"
          ],
          "description": "The error code associated with (only set on \"FAILURE\")"
        }
      },
      "id": "GoogleFirebaseAppdistroV1alphaGetUploadStatusResponse",
      "type": "object"
    },
    "GoogleFirebaseAppdistroV1alphaClearTestCaseCacheRequest": {
      "type": "object",
      "id": "GoogleFirebaseAppdistroV1alphaClearTestCaseCacheRequest",
      "description": "Request message for `ClearTestCaseCache`.",
      "properties": {
        "testDevices": {
          "items": {
            "$ref": "GoogleFirebaseAppdistroV1alphaTestDevice"
          },
          "description": "Optional. The list of devices for which to clear the cache. If not present, clear all of them.",
          "type": "array"
        }
      }
    },
    "GoogleFirebaseAppdistroV1Release": {
      "id": "GoogleFirebaseAppdistroV1Release",
      "type": "object",
      "description": "A release of a Firebase app.",
      "properties": {
        "testingUri": {
          "description": "Output only. A link to the release in the tester web clip or Android app that lets testers (which were granted access to the app) view release notes and install the app onto their devices.",
          "readOnly": true,
          "type": "string"
        },
        "releaseNotes": {
          "description": "Notes of the release.",
          "$ref": "GoogleFirebaseAppdistroV1ReleaseNotes"
        },
        "binaryDownloadUri": {
          "type": "string",
          "description": "Output only. A signed link (which expires in one hour) to directly download the app binary (IPA/APK/AAB) file.",
          "readOnly": true
        },
        "expireTime": {
          "description": "Output only. The time the release will expire.",
          "readOnly": true,
          "type": "string",
          "format": "google-datetime"
        },
        "firebaseConsoleUri": {
          "description": "Output only. A link to the Firebase console displaying a single release.",
          "readOnly": true,
          "type": "string"
        },
        "name": {
          "description": "The name of the release resource. Format: `projects/{project_number}/apps/{app}/releases/{release}`",
          "type": "string"
        },
        "displayVersion": {
          "description": "Output only. Display version of the release. For an Android release, the display version is the `versionName`. For an iOS release, the display version is the `CFBundleShortVersionString`.",
          "readOnly": true,
          "type": "string"
        },
        "buildVersion": {
          "type": "string",
          "description": "Output only. Build version of the release. For an Android release, the build version is the `versionCode`. For an iOS release, the build version is the `CFBundleVersion`.",
          "readOnly": true
        },
        "createTime": {
          "description": "Output only. The time the release was created.",
          "readOnly": true,
          "format": "google-datetime",
          "type": "string"
        },
        "updateTime": {
          "type": "string",
          "format": "google-datetime",
          "description": "Output only. The time the release was last updated.",
          "readOnly": true
        }
      }
    },
    "GoogleFirebaseAppdistroV1UploadReleaseResponse": {
      "id": "GoogleFirebaseAppdistroV1UploadReleaseResponse",
      "type": "object",
      "description": "Response message for `UploadRelease`.",
      "properties": {
        "release": {
          "description": "Release associated with the uploaded binary.",
          "$ref": "GoogleFirebaseAppdistroV1Release"
        },
        "result": {
          "type": "string",
          "enumDescriptions": [
            "Upload binary result unspecified",
            "Upload binary resulted in a new release",
            "Upload binary updated an existing release",
            "Upload binary resulted in a no-op. A release with the exact same binary already exists."
          ],
          "enum": [
            "UPLOAD_RELEASE_RESULT_UNSPECIFIED",
            "RELEASE_CREATED",
            "RELEASE_UPDATED",
            "RELEASE_UNMODIFIED"
          ],
          "description": "Result of upload release."
        }
      }
    },
    "AndroidxCrawlerOutputRectangle": {
      "description": "Rectangle for describing bounding boxes",
      "properties": {
        "right": {
          "type": "integer",
          "format": "int32"
        },
        "bottom": {
          "format": "int32",
          "type": "integer"
        },
        "top": {
          "type": "integer",
          "format": "int32"
        },
        "left": {
          "format": "int32",
          "type": "integer"
        }
      },
      "type": "object",
      "id": "AndroidxCrawlerOutputRectangle"
    },
    "GoogleFirebaseAppdistroV1alphaBatchUpdateTestCasesRequest": {
      "description": "The request message for `BatchUpdateTestCase`.",
      "properties": {
        "requests": {
          "type": "array",
          "items": {
            "$ref": "GoogleFirebaseAppdistroV1alphaUpdateTestCaseRequest"
          },
          "description": "Required. The update requests. A maximum number of 1000 test cases can be updated in one batch"
        }
      },
      "type": "object",
      "id": "GoogleFirebaseAppdistroV1alphaBatchUpdateTestCasesRequest"
    },
    "GoogleFirebaseAppdistroV1alphaListTestCasesResponse": {
      "type": "object",
      "id": "GoogleFirebaseAppdistroV1alphaListTestCasesResponse",
      "description": "The response message for `ListTestCases`.",
      "properties": {
        "testCases": {
          "type": "array",
          "items": {
            "$ref": "GoogleFirebaseAppdistroV1alphaTestCase"
          },
          "description": "The test cases from the specified app."
        },
        "nextPageToken": {
          "description": "A token, which can be sent as `page_token` to retrieve the next page. If this field is omitted, there are no subsequent pages.",
          "type": "string"
        }
      }
    },
    "GoogleFirebaseAppdistroV1ReleaseNotes": {
      "type": "object",
      "id": "GoogleFirebaseAppdistroV1ReleaseNotes",
      "description": "Notes that belong to a release.",
      "properties": {
        "text": {
          "description": "The text of the release notes.",
          "type": "string"
        }
      }
    },
    "GoogleFirebaseAppdistroV1alphaTerminalAction": {
      "description": "An action taken by the AI to end the goal.",
      "properties": {
        "screenshot": {
          "description": "Output only. The screenshot used in the context of this terminal action.",
          "readOnly": true,
          "$ref": "GoogleFirebaseAppdistroV1alphaScreenshot"
        },
        "reason": {
          "readOnly": true,
          "enum": [
            "REASON_UNSPECIFIED",
            "GOAL_IMPOSSIBLE",
            "GOAL_COMPLETE"
          ],
          "description": "Output only. The reason why this goal was ended.",
          "type": "string",
          "enumDescriptions": [
            "Reason unspecified.",
            "The goal failed to be completed. Note that \"impossible\" is a legacy term and the goal is reported to the customer as having \"failed\".",
            "The goal was completed successfully."
          ]
        }
      },
      "type": "object",
      "id": "GoogleFirebaseAppdistroV1alphaTerminalAction"
    },
    "GoogleFirebaseAppdistroV1alphaDeviceInteractionBack": {
      "description": "A back action.",
      "properties": {},
      "id": "GoogleFirebaseAppdistroV1alphaDeviceInteractionBack",
      "type": "object"
    },
    "GoogleFirebaseAppdistroV1alphaGetTesterUdidsResponse": {
      "id": "GoogleFirebaseAppdistroV1alphaGetTesterUdidsResponse",
      "type": "object",
      "description": "Response containing the UDIDs of tester iOS devices in a project",
      "properties": {
        "testerUdids": {
          "type": "array",
          "description": "The UDIDs of tester iOS devices in a project",
          "items": {
            "$ref": "GoogleFirebaseAppdistroV1alphaTesterUdid"
          }
        }
      }
    },
    "GoogleFirebaseAppdistroV1alphaEnableAccessOnReleaseRequest": {
      "id": "GoogleFirebaseAppdistroV1alphaEnableAccessOnReleaseRequest",
      "type": "object",
      "description": "The request message for `EnableAccessOnRelease`.",
      "properties": {
        "displayVersion": {
          "description": "Optional. Ignored. Used to be display version of the app release if an instance identifier was provided for the release_id.",
          "deprecated": true,
          "type": "string"
        },
        "buildVersion": {
          "description": "Optional. Ignored. Used to be build version of the app release if an instance identifier was provided for the release_id.",
          "deprecated": true,
          "type": "string"
        },
        "groupIds": {
          "description": "Optional. A repeated list of group aliases to enable access to a release for Note: This field is misnamed, but can't be changed because we need to maintain compatibility with old build tools",
          "items": {
            "type": "string"
          },
          "type": "array"
        },
        "emails": {
          "type": "array",
          "description": "Optional. An email address which should get access to this release, for example rebeccahe@google.com",
          "items": {
            "type": "string"
          }
        }
      }
    },
    "GoogleFirebaseAppdistroV1alphaDeviceExecution": {
      "description": "The results of running an automated test on a particular device.",
      "properties": {
        "state": {
          "description": "Output only. The state of the test.",
          "type": "string",
          "enumDescriptions": [
            "Test state unspecified.",
            "The test is in progress.",
            "The test has passed.",
            "The test has failed.",
            "The test was inconclusive."
          ],
          "readOnly": true,
          "enum": [
            "TEST_STATE_UNSPECIFIED",
            "IN_PROGRESS",
            "PASSED",
            "FAILED",
            "INCONCLUSIVE"
          ]
        },
        "appCrash": {
          "description": "Output only. An app crash, if any occurred during the test.",
          "readOnly": true,
          "$ref": "GoogleFirebaseAppdistroV1alphaAppCrash"
        },
        "finalAiAssertionMissing": {
          "description": "Output only. Indicates that the test replayed saved actions and concluded without a final AI assertion.",
          "readOnly": true,
          "type": "boolean"
        },
        "aiStepResults": {
          "type": "array",
          "items": {
            "$ref": "GoogleFirebaseAppdistroV1alphaAiStepResult"
          },
          "description": "Output only. Results of the AI steps if passed in",
          "readOnly": true
        },
        "failedReason": {
          "description": "Output only. The reason why the test failed.",
          "type": "string",
          "enumDescriptions": [
            "Reason unspecified.",
            "The app crashed during the test.",
            "If an app is not installed and thus no test can be run with the app. This might be caused by trying to run a test on an unsupported platform.",
            "If the app could not be crawled (possibly because the app did not start).",
            "If the device ran out of memory during the test.",
            "At least one AI step failed.",
            "The crawl reached the time limit before the test could be completed."
          ],
          "readOnly": true,
          "enum": [
            "FAILED_REASON_UNSPECIFIED",
            "CRASHED",
            "NOT_INSTALLED",
            "UNABLE_TO_CRAWL",
            "DEVICE_OUT_OF_MEMORY",
            "FAILED_AI_STEP",
            "TIMED_OUT"
          ]
        },
        "crawlGraphUri": {
          "type": "string",
          "description": "Output only. A URI to an image of the Robo crawl graph.",
          "readOnly": true
        },
        "screenshotUris": {
          "type": "array",
          "items": {
            "type": "string"
          },
          "description": "Output only. A list of screenshot image URIs taken from the Robo crawl. The file names are numbered by the order in which they were taken.",
          "readOnly": true
        },
        "name": {
          "description": "Identifier. The name of the device execution resource. Format: `projects/{project_number}/apps/{app}/releases/{release}/tests/{test}/deviceExecutions/{device_execution}`",
          "type": "string"
        },
        "inconclusiveReason": {
          "readOnly": true,
          "enum": [
            "INCONCLUSIVE_REASON_UNSPECIFIED",
            "QUOTA_EXCEEDED",
            "INFRASTRUCTURE_FAILURE",
            "SERVICE_NOT_ACTIVATED",
            "NO_SIGNATURE",
            "NO_LAUNCHER_ACTIVITY",
            "FORBIDDEN_PERMISSIONS",
            "DEVICE_ADMIN_RECEIVER",
            "NO_CODE_APK",
            "INVALID_APK_PREVIEW_SDK"
          ],
          "description": "Output only. The reason why the test was inconclusive.",
          "type": "string",
          "enumDescriptions": [
            "Reason unspecified.",
            "Not enough quota remained to run the test.",
            "The outcome of the test could not be determined because of a failure in the test running infrastructure.",
            "A required cloud service api is not activated (Google Cloud Testing API or Cloud Tool Results API).",
            "The app was not signed.",
            "A main launcher activity could not be found.",
            "The app declares one or more permissions that are not allowed.",
            "Device administrator applications are not allowed.",
            "APK contains no code. See also https://developer.android.com/guide/topics/manifest/application-element.html#code",
            "APK is built for a preview SDK which is unsupported."
          ]
        },
        "resultsStoragePath": {
          "description": "Output only. The path to a directory in Cloud Storage that will eventually contain the results for this execution. For example, gs://bucket/Nexus5-18-en-portrait.",
          "readOnly": true,
          "type": "string"
        },
        "videoStartTime": {
          "type": "string",
          "format": "google-datetime",
          "description": "Output only. The time at which the video started recording.",
          "readOnly": true
        },
        "device": {
          "description": "Required. The device that the test was run on.",
          "$ref": "GoogleFirebaseAppdistroV1alphaTestDevice"
        },
        "roboStats": {
          "description": "Output only. The statistics collected during the Robo test.",
          "readOnly": true,
          "$ref": "GoogleFirebaseAppdistroV1alphaRoboStats"
        },
        "originDeviceExecution": {
          "description": "Output only. The device execution from which cached steps were used during this execution. Note: This field is only populated for ACTION_BASED_REPLAY executions. If the original device execution no longer exists, this field will be empty. Format: `projects/{project_number}/apps/{app}/releases/{release}/tests/{test}/deviceExecutions/{device_execution}`",
          "readOnly": true,
          "type": "string"
        },
        "executionType": {
          "readOnly": true,
          "enum": [
            "EXECUTION_TYPE_UNSPECIFIED",
            "AI",
            "ACTION_BASED_REPLAY",
            "AI_REPLAY",
            "RANDOM_CRAWL"
          ],
          "description": "Output only. The type of execution for the test.",
          "type": "string",
          "enumDescriptions": [
            "Execution type unspecified.",
            "An AI-driven test.",
            "A replay of a previous test run.",
            "A failed replay that was rerun using the AI agent.",
            "A random Robo test."
          ]
        },
        "videoUri": {
          "type": "string",
          "description": "Output only. A URI to a video of the test run.",
          "readOnly": true
        }
      },
      "id": "GoogleFirebaseAppdistroV1alphaDeviceExecution",
      "type": "object"
    },
    "GoogleFirebaseAppdistroV1alphaTestDevice": {
      "id": "GoogleFirebaseAppdistroV1alphaTestDevice",
      "type": "object",
      "description": "A device on which automated tests can be run.",
      "properties": {
        "version": {
          "type": "string",
          "description": "Required. The version of the device (API level on Android)."
        },
        "orientation": {
          "description": "Optional. The orientation of the device during the test.",
          "type": "string"
        },
        "model": {
          "description": "Required. The device model.",
          "type": "string"
        },
        "locale": {
          "description": "Optional. The locale of the device (e.g. \"en_US\" for US English) during the test.",
          "type": "string"
        }
      }
    },
    "GoogleFirebaseAppdistroV1alphaApp": {
      "description": "An app.",
      "properties": {
        "appId": {
          "description": "Firebase gmp app id",
          "type": "string"
        },
        "projectNumber": {
          "description": "Project number of the Firebase project, for example 300830567303.",
          "type": "string"
        },
        "contactEmail": {
          "type": "string",
          "description": "Developer contact email for testers to reach out to about privacy or support issues."
        },
        "bundleId": {
          "type": "string",
          "description": "Bundle identifier"
        },
        "aabState": {
          "description": "App bundle state. Only valid for android apps. The app_view field in the request must be set to FULL in order for this to be populated.",
          "type": "string",
          "enumDescriptions": [
            "Aab state unspecified",
            "App can receive app bundle uploads",
            "Firebase project is not linked to a Play developer account",
            "There is no app in linked Play developer account with the same bundle id",
            "The app in Play developer account is not in a published state",
            "Play App status is unavailable",
            "Play IAS terms not accepted"
          ],
          "enum": [
            "AAB_STATE_UNSPECIFIED",
            "ACTIVE",
            "PLAY_ACCOUNT_NOT_LINKED",
            "NO_APP_WITH_GIVEN_BUNDLE_ID_IN_PLAY_ACCOUNT",
            "APP_NOT_PUBLISHED",
            "AAB_STATE_UNAVAILABLE",
            "PLAY_IAS_TERMS_NOT_ACCEPTED"
          ]
        },
        "platform": {
          "description": "iOS or Android",
          "type": "string"
        },
        "aabCertificate": {
          "description": "App bundle test certificate generated for the app.",
          "$ref": "GoogleFirebaseAppdistroV1alphaAabCertificate"
        }
      },
      "type": "object",
      "id": "GoogleFirebaseAppdistroV1alphaApp"
    },
    "GoogleFirebaseAppdistroV1alphaAiStepResult": {
      "type": "object",
      "id": "GoogleFirebaseAppdistroV1alphaAiStepResult",
      "description": "Captures the results of an AiStep",
      "properties": {
        "step": {
          "description": "Required. The step performed by the AI",
          "$ref": "GoogleFirebaseAppdistroV1alphaAiStep"
        },
        "goalDetails": {
          "description": "Output only. Details for a goal step.",
          "readOnly": true,
          "$ref": "GoogleFirebaseAppdistroV1alphaGoalDetails"
        },
        "state": {
          "description": "Output only. The current state of the step",
          "type": "string",
          "enumDescriptions": [
            "Step state unspecified",
            "The step is in progress",
            "The step has completed successfully",
            "The step has failed",
            "The test timed out during this step",
            "The number of actions needed to reach the goal exceeded its limit"
          ],
          "readOnly": true,
          "enum": [
            "STEP_STATE_UNSPECIFIED",
            "IN_PROGRESS",
            "PASSED",
            "FAILED",
            "TIMED_OUT",
            "GOAL_ACTION_LIMIT_REACHED"
          ]
        },
        "assertionDetails": {
          "description": "Output only. Details for an assertion step.",
          "readOnly": true,
          "$ref": "GoogleFirebaseAppdistroV1alphaAssertionDetails"
        }
      }
    },
    "GoogleFirebaseAppdistroV1alphaAiStep": {
      "id": "GoogleFirebaseAppdistroV1alphaAiStep",
      "type": "object",
      "description": "A step to be accomplished by the AI",
      "properties": {
        "testCase": {
          "description": "Output only. The test case that contained this step. Note: The test case may have changed or been deleted since this step was created. Format: `projects/{project_number}/apps/{app}/testCases/{test_case}`",
          "readOnly": true,
          "type": "string"
        },
        "goal": {
          "description": "A goal to be accomplished by the AI",
          "type": "string"
        },
        "hint": {
          "description": "Optional. Hint text containing suggestions to help the agent accomplish the goal",
          "type": "string"
        },
        "assertion": {
          "description": "An assertion to be checked by the AI",
          "type": "string"
        },
        "successCriteria": {
          "description": "Optional. A visual description of the screen's expected state after the step has been successfully completed. This is referred to as the \"final screen assertion\" in the Firebase console and CLI tools. This field must be provided for the last step in a test case, and is optional for all other steps.",
          "type": "string"
        }
      }
    },
    "GoogleFirebaseAppdistroV1UploadReleaseMetadata": {
      "type": "object",
      "id": "GoogleFirebaseAppdistroV1UploadReleaseMetadata",
      "description": "Operation metadata for `UploadRelease`.",
      "properties": {}
    },
    "GoogleFirebaseAppdistroV1alphaAssertionDetails": {
      "type": "object",
      "id": "GoogleFirebaseAppdistroV1alphaAssertionDetails",
      "description": "Details for an assertion step.",
      "properties": {
        "screenshot": {
          "description": "Output only. The screenshot used in the context of this assertion.",
          "readOnly": true,
          "$ref": "GoogleFirebaseAppdistroV1alphaScreenshot"
        },
        "result": {
          "type": "boolean",
          "description": "Output only. The result of the assertion.",
          "readOnly": true
        },
        "explanation": {
          "description": "Output only. An explanation justifying the assertion result.",
          "readOnly": true,
          "type": "string"
        }
      }
    },
    "GoogleFirebaseAppdistroV1alphaDeviceInteractionWait": {
      "type": "object",
      "id": "GoogleFirebaseAppdistroV1alphaDeviceInteractionWait",
      "description": "A wait action.",
      "properties": {
        "duration": {
          "type": "string",
          "format": "google-duration",
          "description": "Output only. The duration of the wait.",
          "readOnly": true
        }
      }
    },
    "GoogleFirebaseAppdistroV1alphaRelease": {
      "description": "Proto defining a release object",
      "properties": {
        "instanceId": {
          "description": "Instance id of the release",
          "type": "string"
        },
        "openInvitationCount": {
          "format": "int32",
          "type": "integer",
          "description": "Number of testers who have open invitations for the release"
        },
        "testerWithInstallCount": {
          "format": "int32",
          "type": "integer",
          "description": "Number of testers who have installed the release"
        },
        "testerCount": {
          "type": "integer",
          "format": "int32",
          "description": "Count of testers added to the release"
        },
        "id": {
          "type": "string",
          "description": "Release Id"
        },
        "distributedAt": {
          "type": "string",
          "format": "google-datetime",
          "description": "Timestamp when the release was created"
        },
        "releaseNotesSummary": {
          "description": "Release notes summary",
          "type": "string"
        },
        "buildVersion": {
          "type": "string",
          "description": "Release build version"
        },
        "lastActivityAt": {
          "type": "string",
          "format": "google-datetime",
          "description": "Last activity timestamp"
        },
        "receivedAt": {
          "deprecated": true,
          "format": "google-datetime",
          "type": "string",
          "description": "unused. "
        },
        "displayVersion": {
          "description": "Release version",
          "type": "string"
        }
      },
      "type": "object",
      "id": "GoogleFirebaseAppdistroV1alphaRelease"
    },
    "GoogleFirebaseAppdistroV1alphaCreateReleaseNotesRequest": {
      "description": "The request message for `CreateReleaseNotes`.",
      "properties": {
        "releaseNotes": {
          "description": "The actual release notes body from the user",
          "$ref": "GoogleFirebaseAppdistroV1alphaReleaseNotes"
        }
      },
      "type": "object",
      "id": "GoogleFirebaseAppdistroV1alphaCreateReleaseNotesRequest"
    },
    "GoogleFirebaseAppdistroV1alphaGetReleaseByUploadHashResponse": {
      "id": "GoogleFirebaseAppdistroV1alphaGetReleaseByUploadHashResponse",
      "type": "object",
      "description": "Response object to get the release given a upload hash",
      "properties": {
        "release": {
          "description": "Release object",
          "$ref": "GoogleFirebaseAppdistroV1alphaRelease"
        }
      }
    },
    "GoogleProtobufEmpty": {
      "id": "GoogleProtobufEmpty",
      "type": "object",
      "description": "A generic empty message that you can re-use to avoid defining duplicated empty messages in your APIs. A typical example is to use it as the request or the response type of an API method. For instance: service Foo { rpc Bar(google.protobuf.Empty) returns (google.protobuf.Empty); }",
      "properties": {}
    },
    "GoogleFirebaseAppdistroV1alphaReleaseTest": {
      "description": "Instance of an automated test for a release.",
      "properties": {
        "deviceExecutions": {
          "type": "array",
          "description": "Required. The results of the test on each device.",
          "items": {
            "$ref": "GoogleFirebaseAppdistroV1alphaDeviceExecution"
          }
        },
        "aiInstructions": {
          "description": "Optional. Instructions for AI driven test.",
          "$ref": "GoogleFirebaseAppdistroV1alphaAiInstructions"
        },
        "displayName": {
          "description": "Optional. Display name of the release test. Required if the release test is created with multiple goals.",
          "type": "string"
        },
        "createTime": {
          "description": "Output only. Timestamp when the test was run.",
          "readOnly": true,
          "type": "string",
          "format": "google-datetime"
        },
        "loginCredential": {
          "description": "Optional. Input only. Login credentials for the test. Input only.",
          "$ref": "GoogleFirebaseAppdistroV1alphaLoginCredential"
        },
        "testState": {
          "type": "string",
          "enumDescriptions": [
            "Test state unspecified.",
            "The test is in progress.",
            "The test has passed.",
            "The test has failed.",
            "The test was inconclusive."
          ],
          "description": "Output only. The state of the release test.",
          "enum": [
            "TEST_STATE_UNSPECIFIED",
            "IN_PROGRESS",
            "PASSED",
            "FAILED",
            "INCONCLUSIVE"
          ],
          "readOnly": true
        },
        "testCase": {
          "description": "Optional. The test case that was used to generate this release test. Note: The test case may have changed or been deleted since the release test was created. Format: `projects/{project_number}/apps/{app}/testCases/{test_case}`",
          "type": "string"
        },
        "name": {
          "type": "string",
          "description": "The name of the release test resource. Format: `projects/{project_number}/apps/{app}/releases/{release}/tests/{test}`"
        }
      },
      "type": "object",
      "id": "GoogleFirebaseAppdistroV1alphaReleaseTest"
    },
    "GoogleFirebaseAppdistroV1alphaTesterUdid": {
      "id": "GoogleFirebaseAppdistroV1alphaTesterUdid",
      "type": "object",
      "description": "The UDIDs of a tester's iOS device",
      "properties": {
        "udid": {
          "description": "The UDID of the tester's device",
          "type": "string"
        },
        "name": {
          "description": "The name of the tester's device",
          "type": "string"
        },
        "platform": {
          "description": "The platform of the tester's device",
          "type": "string"
        }
      }
    },
    "GoogleFirebaseAppdistroV1alphaAiInstructions": {
      "type": "object",
      "id": "GoogleFirebaseAppdistroV1alphaAiInstructions",
      "properties": {
        "steps": {
          "description": "Required. Steps to be accomplished by the AI",
          "items": {
            "$ref": "GoogleFirebaseAppdistroV1alphaAiStep"
          },
          "type": "array"
        }
      }
    },
    "GoogleFirebaseAppdistroV1alphaScreenshot": {
      "description": "A device screenshot taken during a test.",
      "properties": {
        "height": {
          "description": "Output only. The height of the screenshot, in pixels.",
          "readOnly": true,
          "format": "int32",
          "type": "integer"
        },
        "width": {
          "format": "int32",
          "type": "integer",
          "description": "Output only. The width of the screenshot, in pixels.",
          "readOnly": true
        },
        "uri": {
          "type": "string",
          "description": "Output only. The URI of the screenshot.",
          "readOnly": true
        }
      },
      "type": "object",
      "id": "GoogleFirebaseAppdistroV1alphaScreenshot"
    },
    "GoogleFirebaseAppdistroV1alphaAppCrash": {
      "description": "An app crash that occurred during an automated test.",
      "properties": {
        "stackTrace": {
          "type": "string",
          "description": "Output only. The raw stack trace.",
          "readOnly": true
        },
        "message": {
          "type": "string",
          "description": "Output only. The message associated with the crash.",
          "readOnly": true
        }
      },
      "type": "object",
      "id": "GoogleFirebaseAppdistroV1alphaAppCrash"
    },
    "GoogleFirebaseAppdistroV1alphaBatchDeleteTestCasesRequest": {
      "type": "object",
      "id": "GoogleFirebaseAppdistroV1alphaBatchDeleteTestCasesRequest",
      "description": "The request message for `BatchDeleteTestCase`.",
      "properties": {
        "names": {
          "type": "array",
          "description": "Required. The name of the test cases to delete. A maximum number of 1000 test cases can be deleted in one batch Format: `projects/{project_number}/apps/{app}/testCases/{test_case}`",
          "items": {
            "type": "string"
          }
        }
      }
    },
    "GoogleFirebaseAppdistroV1alphaGoalActionDebugInfo": {
      "description": "Information to help the customer understand why the agent took this action.",
      "properties": {
        "annotatedScreenshotUri": {
          "type": "string",
          "description": "Output only. URI of the screenshot with elements labeled which was used by the agent.",
          "readOnly": true
        },
        "jsonUri": {
          "description": "Output only. Structured data explaining the agent's choice.",
          "readOnly": true,
          "type": "string"
        }
      },
      "id": "GoogleFirebaseAppdistroV1alphaGoalActionDebugInfo",
      "type": "object"
    },
    "GoogleFirebaseAppdistroV1alphaDeviceInteractionDragAndDrop": {
      "type": "object",
      "id": "GoogleFirebaseAppdistroV1alphaDeviceInteractionDragAndDrop",
      "description": "A drag and drop action.",
      "properties": {
        "start": {
          "description": "Output only. The start point of the drag and drop.",
          "readOnly": true,
          "$ref": "AndroidxCrawlerOutputPoint"
        },
        "end": {
          "description": "Output only. The end point of the drag and drop.",
          "readOnly": true,
          "$ref": "AndroidxCrawlerOutputPoint"
        }
      }
    },
    "GoogleFirebaseAppdistroV1alphaEnableAccessOnReleaseResponse": {
      "type": "object",
      "id": "GoogleFirebaseAppdistroV1alphaEnableAccessOnReleaseResponse",
      "description": "The response message for `EnableAccessOnRelease`.",
      "properties": {}
    },
    "GoogleFirebaseAppdistroV1alphaTestConfig": {
      "description": "Configuration for automated tests",
      "properties": {
        "name": {
          "type": "string",
          "description": "Identifier. The name of the test configuration resource. Format: `projects/{project_number}/apps/{app}/testConfig`"
        },
        "displayName": {
          "type": "string",
          "description": "Optional. Display name of the AI driven test. Required if the release test is created with multiple goals."
        },
        "testDevices": {
          "type": "array",
          "description": "Optional. Tests will be run on this list of devices",
          "items": {
            "$ref": "GoogleFirebaseAppdistroV1alphaTestDevice"
          }
        },
        "roboCrawler": {
          "description": "Optional. Configuration for Robo crawler",
          "$ref": "GoogleFirebaseAppdistroV1alphaRoboCrawler"
        }
      },
      "id": "GoogleFirebaseAppdistroV1alphaTestConfig",
      "type": "object"
    },
    "GoogleFirebaseAppdistroV1alphaDeviceInteractionSwipe": {
      "description": "A swipe action.",
      "properties": {
        "end": {
          "description": "Output only. The end point of the swipe.",
          "readOnly": true,
          "$ref": "AndroidxCrawlerOutputPoint"
        },
        "start": {
          "description": "Output only. The start point of the swipe.",
          "readOnly": true,
          "$ref": "AndroidxCrawlerOutputPoint"
        }
      },
      "id": "GoogleFirebaseAppdistroV1alphaDeviceInteractionSwipe",
      "type": "object"
    },
    "GoogleFirebaseAppdistroV1alphaTestQuota": {
      "description": "Customer quota information for `ReleaseTests`. Note: This quota only applies to tests with `AiInstructions` and is separate from the quota which might apply to the device time used by any tests.",
      "properties": {
        "usage": {
          "description": "Output only. Number of `ReleaseTests` run in the current month",
          "readOnly": true,
          "format": "int64",
          "type": "string"
        },
        "name": {
          "description": "Identifier. The name of the `TestQuota` resource. Format: `projects/{project_number}/testQuota`",
          "type": "string"
        },
        "limit": {
          "description": "Output only. Maximum number of `ReleaseTests` allotted for the current month.",
          "readOnly": true,
          "format": "int64",
          "type": "string"
        }
      },
      "id": "GoogleFirebaseAppdistroV1alphaTestQuota",
      "type": "object"
    },
    "GoogleFirebaseAppdistroV1alphaCancelReleaseTestResponse": {
      "description": "The (empty) response message for `CancelReleaseTest`.",
      "properties": {},
      "id": "GoogleFirebaseAppdistroV1alphaCancelReleaseTestResponse",
      "type": "object"
    },
    "GoogleFirebaseAppdistroV1alphaBatchUpdateTestCasesResponse": {
      "type": "object",
      "id": "GoogleFirebaseAppdistroV1alphaBatchUpdateTestCasesResponse",
      "description": "The response message for `BatchUpdateTestCase`.",
      "properties": {
        "testCases": {
          "description": "The updated test cases.",
          "items": {
            "$ref": "GoogleFirebaseAppdistroV1alphaTestCase"
          },
          "type": "array"
        }
      }
    },
    "AndroidxCrawlerOutputPoint": {
      "id": "AndroidxCrawlerOutputPoint",
      "type": "object",
      "description": "Point for describing bounding boxes tap locations Top left is 0,0",
      "properties": {
        "xCoordinate": {
          "format": "int32",
          "type": "integer"
        },
        "yCoordinate": {
          "type": "integer",
          "format": "int32"
        }
      }
    },
    "GoogleFirebaseAppdistroV1alphaRoboCrawler": {
      "type": "object",
      "id": "GoogleFirebaseAppdistroV1alphaRoboCrawler",
      "description": "Configuration for Robo crawler",
      "properties": {
        "loginCredential": {
          "description": "Optional. Login credential for automated tests",
          "$ref": "GoogleFirebaseAppdistroV1alphaLoginCredential"
        },
        "aiInstructions": {
          "description": "Optional. Instructions for AI driven test",
          "$ref": "GoogleFirebaseAppdistroV1alphaAiInstructions"
        }
      }
    },
    "GoogleFirebaseAppdistroV1alphaAabCertificate": {
      "description": "App bundle test certificate",
      "properties": {
        "certificateHashMd5": {
          "description": "MD5 hash of the certificate used to resign the AAB",
          "type": "string"
        },
        "certificateHashSha1": {
          "description": "SHA1 hash of the certificate used to resign the AAB",
          "type": "string"
        },
        "certificateHashSha256": {
          "description": "SHA256 hash of the certificate used to resign the AAB",
          "type": "string"
        }
      },
      "type": "object",
      "id": "GoogleFirebaseAppdistroV1alphaAabCertificate"
    },
    "GoogleFirebaseAppdistroV1alphaDeviceInteractionEnterText": {
      "id": "GoogleFirebaseAppdistroV1alphaDeviceInteractionEnterText",
      "type": "object",
      "description": "A text entry action, that enters text into a particular text field, clearing any existing text in the field.",
      "properties": {
        "elementBounds": {
          "description": "Output only. The visible bounds of the element to enter text into.",
          "readOnly": true,
          "$ref": "AndroidxCrawlerOutputRectangle"
        },
        "text": {
          "type": "string",
          "description": "Output only. The text to enter.",
          "readOnly": true
        }
      }
    },
    "GoogleFirebaseAppdistroV1alphaListReleaseTestsResponse": {
      "id": "GoogleFirebaseAppdistroV1alphaListReleaseTestsResponse",
      "type": "object",
      "description": "The response message for `ListReleaseTests`.",
      "properties": {
        "releaseTests": {
          "description": "The tests listed.",
          "items": {
            "$ref": "GoogleFirebaseAppdistroV1alphaReleaseTest"
          },
          "type": "array"
        },
        "nextPageToken": {
          "type": "string",
          "description": "A short-lived token, which can be sent as `pageToken` to retrieve the next page. If this field is omitted, there are no subsequent pages."
        }
      }
    },
    "GoogleFirebaseAppdistroV1alphaUpdateTestCaseRequest": {
      "type": "object",
      "id": "GoogleFirebaseAppdistroV1alphaUpdateTestCaseRequest",
      "description": "The request message for `UpdateTestCase`.",
      "properties": {
        "testCase": {
          "description": "Required. The test case to update. The test case's `name` field is used to identify the test case to update. Format: `projects/{project_number}/apps/{app}/testCases/{test_case}`",
          "$ref": "GoogleFirebaseAppdistroV1alphaTestCase"
        },
        "allowMissing": {
          "type": "boolean",
          "description": "Optional. If set to true, and the test case is not found, a new test case will be created."
        }
      }
    },
    "GoogleFirebaseAppdistroV1alphaLoginCredentialFieldHints": {
      "id": "GoogleFirebaseAppdistroV1alphaLoginCredentialFieldHints",
      "type": "object",
      "description": "Hints to the crawler for identifying input fields",
      "properties": {
        "passwordResourceName": {
          "type": "string",
          "description": "Required. The Android resource name of the password UI element. For example, in Java: R.string.foo in xml: @string/foo Only the \"foo\" part is needed. Reference doc: https://developer.android.com/guide/topics/resources/accessing-resources.html"
        },
        "usernameResourceName": {
          "type": "string",
          "description": "Required. The Android resource name of the username UI element. For example, in Java: R.string.foo in xml: @string/foo Only the \"foo\" part is needed. Reference doc: https://developer.android.com/guide/topics/resources/accessing-resources.html"
        }
      }
    }
  },
  "description": "",
  "batchPath": "batch"
}